mvesuvio/__init__.py
mvesuvio/_version.py
mvesuvio/analysis_fitting.py
mvesuvio/analysis_reduction.py
mvesuvio/globals.py
mvesuvio/config/Mantid.user.properties
mvesuvio/config/__init__.py
mvesuvio/config/analysis_inputs.py
mvesuvio/config/script_to_create_figures.py
mvesuvio/config/vesuvio.plots.mplstyle
mvesuvio/config/vesuvio.user.properties
mvesuvio/config/ip_files/__init__.py
mvesuvio/config/ip_files/ip2018.par
mvesuvio/config/ip_files/ip2018_2.par
mvesuvio/config/ip_files/ip2018_3.par
mvesuvio/config/ip_files/ip2019.par
mvesuvio/main/__init__.py
mvesuvio/main/run_routine.py
mvesuvio/util/__init__.py
mvesuvio/util/analysis_helpers.py
mvesuvio/util/handle_config.py
mvesuvio-0.1.dev14.dist-info/METADATA
mvesuvio-0.1.dev14.dist-info/WHEEL
mvesuvio-0.1.dev14.dist-info/entry_points.txt
mvesuvio-0.1.dev14.dist-info/top_level.txt
mvesuvio-0.1.dev14.dist-info/RECORD
