Metadata-Version: 2.4
Name: mvesuvio
Version: 0.1.dev14
Summary: Analyse Vesuvio instrument data
Author-email: The Mantid Project <mantid-help@mantidproject.org>, Guilherme Pereira <gui.maciel-pereira@stfc.ac.uk>
Project-URL: Repository, https://github.com/mantidproject/vesuvio
Project-URL: Bug Tracker, https://github.com/mantidproject/vesuvio/issues
Classifier: Programming Language :: Python :: 3.11
Classifier: License :: OSI Approved :: GNU General Public License v3 (GPLv3)
Classifier: Operating System :: OS Independent
Classifier: Topic :: Scientific/Engineering
Requires-Python: >=3.8
Requires-Dist: iminuit
Requires-Dist: jacobi
Requires-Dist: dill
